src/__init__.py
src/main.py
src/lib/__init__.py
src/lib/api.py
src/lib/general.py
src/lib/geo.py
src/lib/stream.py
src/tests/__init__.py
src/tests/api_unittests.py
src/tests/general_unittests.py
src/tests/geo_unittests.py
src/tests/stream_unittests.py
geoville_streaming_toolbox-1.0.0.dist-info/METADATA
geoville_streaming_toolbox-1.0.0.dist-info/WHEEL
geoville_streaming_toolbox-1.0.0.dist-info/top_level.txt
geoville_streaming_toolbox-1.0.0.dist-info/RECORD
